{"settings":{"nativeScrollbars":true,"nativeScrollbarsThin":true,"nativeScrollbarsLeft":false,"selWinScreenshots":false,"updateSidebarTitle":true,"markWindow":false,"markWindowPreface":"","ctxMenuNative":true,"ctxMenuRenderInact":false,"ctxMenuRenderIcons":true,"ctxMenuIgnoreContainers":"","navBarLayout":"hidden","navBarInline":true,"navBarSide":"left","hideAddBtn":false,"hideSettingsBtn":false,"navBtnCount":true,"hideEmptyPanels":true,"hideDiscardedTabPanels":false,"navActTabsPanelLeftClickAction":"none","navActBookmarksPanelLeftClickAction":"none","navTabsPanelMidClickAction":"discard","navBookmarksPanelMidClickAction":"none","navSwitchPanelsWheel":true,"subPanelRecentlyClosedBar":true,"subPanelBookmarks":true,"subPanelHistory":true,"groupLayout":"grid","skipEmptyPanels":false,"dndTabAct":true,"dndTabActDelay":750,"dndTabActMod":"none","dndExp":"pointer","dndExpDelay":0,"dndExpMod":"none","dndOutside":"win","dndActTabFromLink":true,"dndActSearchTab":true,"dndMoveTabs":false,"dndMoveBookmarks":false,"searchBarMode":"dynamic","searchBookmarksShortcut":"","searchHistoryShortcut":"","warnOnMultiTabClose":"collapsed","activateLastTabOnPanelSwitching":true,"activateLastTabOnPanelSwitchingLoadedOnly":true,"switchPanelAfterSwitchingTab":"always","tabRmBtn":"hover","activateAfterClosing":"prev_act","activateAfterClosingStayInPanel":false,"activateAfterClosingGlobal":true,"activateAfterClosingNoFolded":true,"activateAfterClosingNoDiscarded":true,"askNewBookmarkPlace":false,"tabsRmUndoNote":true,"tabsUnreadMark":false,"tabsUpdateMark":"all","tabsUpdateMarkFirst":true,"tabsReloadLimit":5,"tabsReloadLimitNotif":true,"showNewTabBtns":true,"newTabBarPosition":"after_tabs","tabsPanelSwitchActMove":true,"tabsPanelSwitchActMoveAuto":true,"tabsUrlInTooltip":"none","newTabCtxReopen":false,"moveNewTabPin":"end","moveNewTabParent":"last_child","moveNewTabParentActPanel":false,"moveNewTab":"end","moveNewTabActivePin":"start","pinnedTabsPosition":"top","pinnedTabsList":true,"pinnedAutoGroup":false,"pinnedNoUnload":false,"tabsTree":true,"groupOnOpen":true,"tabsTreeLimit":1,"autoFoldTabs":false,"autoFoldTabsExcept":"none","autoExpandTabs":false,"autoExpandTabsOnNew":false,"rmChildTabs":"folded","tabsChildCount":true,"tabsLvlDots":false,"discardFolded":false,"discardFoldedDelay":0,"discardFoldedDelayUnit":"sec","tabsTreeBookmarks":true,"treeRmOutdent":"first_child","ignoreFoldedParent":false,"colorizeTabs":false,"colorizeTabsSrc":"domain","colorizeTabsBranches":true,"colorizeTabsBranchesSrc":"domain","inheritCustomColor":true,"hideInact":false,"hideFoldedTabs":true,"hideFoldedParent":"none","nativeHighlight":false,"warnOnMultiBookmarkDelete":"collapsed","autoCloseBookmarks":true,"autoRemoveOther":false,"highlightOpenBookmarks":false,"activateOpenBookmarkTab":false,"showBookmarkLen":true,"bookmarksRmUndoNote":true,"loadBookmarksOnDemand":true,"pinOpenedBookmarksFolder":true,"oldBookmarksAfterSave":"ask","loadHistoryOnDemand":true,"fontSize":"s","animations":true,"animationSpeed":"fast","theme":"proton","density":"default","colorScheme":"ff","sidebarCSS":true,"groupCSS":false,"snapNotify":true,"snapExcludePrivate":false,"snapInterval":1,"snapIntervalUnit":"day","snapLimit":0,"snapLimitUnit":"snap","snapAutoExport":false,"snapAutoExportType":"json","snapAutoExportPath":"Sidebery/snapshot-%Y.%M.%D-%h.%m.%s","snapMdFullTree":false,"hScrollAction":"none","navSwitchPanelsDelay":128,"scrollThroughTabs":"none","scrollThroughVisibleTabs":false,"scrollThroughTabsSkipDiscarded":false,"scrollThroughTabsExceptOverflow":true,"scrollThroughTabsCyclic":false,"scrollThroughTabsScrollArea":0,"autoMenuMultiSel":true,"multipleMiddleClose":false,"longClickDelay":500,"wheelThreshold":false,"wheelThresholdX":10,"wheelThresholdY":60,"tabDoubleClick":"none","tabsSecondClickActPrev":true,"tabsSecondClickActPrevPanelOnly":false,"shiftSelAct":true,"activateOnMouseUp":true,"tabLongLeftClick":"none","tabLongRightClick":"none","tabCloseMiddleClick":"close","tabsPanelLeftClickAction":"none","tabsPanelDoubleClickAction":"tab","tabsPanelRightClickAction":"menu","tabsPanelMiddleClickAction":"tab","newTabMiddleClickAction":"new_child","bookmarksLeftClickAction":"open_in_act","bookmarksLeftClickActivate":false,"bookmarksLeftClickPos":"default","bookmarksMidClickAction":"open_in_new","bookmarksMidClickActivate":false,"bookmarksMidClickRemove":false,"bookmarksMidClickPos":"default","syncName":"Firefox Desktop","syncSaveSettings":true,"syncSaveCtxMenu":true,"syncSaveStyles":true,"syncSaveKeybindings":false,"selectActiveTabFirst":true},"sidebar":{"panels":{"bookmarks":{"type":1,"id":"bookmarks","name":"Bookmarks","iconSVG":"icon_bookmarks","iconIMGSrc":"","iconIMG":"","color":"toolbar","lockedPanel":false,"tempMode":false,"skipOnSwitching":false,"rootId":"root________","viewMode":"tree","autoConvert":false,"srcPanelConfig":null},"firefox-default":{"type":2,"id":"firefox-default","name":"Default","color":"toolbar","iconSVG":"icon_tabs","lockedPanel":false,"skipOnSwitching":false,"noEmpty":false,"newTabCtx":"none","dropTabCtx":"none","moveRules":[],"moveExcludedTo":-1,"bookmarksFolderId":-1,"newTabBtns":[],"srcPanelConfig":null}},"nav":["bookmarks","firefox-default","add_tp","sp-0","settings"]},"contextMenu":{"tabs":[{"opts":["undoRmTab","mute","reload","bookmark"]},"separator-1",{"name":"%menu.tab.move_to_sub_menu_name","opts":["moveToNewWin","moveToWin","separator-5","moveToPanel","moveToNewPanel"]},{"name":"%menu.tab.reopen_in_sub_menu_name","opts":["reopenInNewWin","reopenInWin","reopenInCtr","reopenInNewCtr"]},{"name":"%menu.tab.colorize_","opts":["colorizeTab"]},"separator-2","pin","duplicate","discard","copyTabsUrls","copyTabsTitles","separator-3","group","flatten","separator-4","close"],"tabsPanel":[{"opts":["undoRmTab","muteAllAudibleTabs","reloadTabs","discardTabs"]},"separator-7","selectAllTabs","collapseInactiveBranches","closeTabsDuplicates","closeTabs","separator-8","separator-9"],"bookmarks":[{"name":"%menu.bookmark.open_in_sub_menu_name","opts":["openInNewWin","openInNewPrivWin","separator-9","openInPanel","openInNewPanel","separator-10","openInCtr"]},{"name":"%menu.bookmark.sort_sub_menu_name","opts":["sortByNameAscending","sortByNameDescending","sortByLinkAscending","sortByLinkDescending","sortByTimeAscending","sortByTimeDescending"]},"separator-5","createBookmark","createFolder","createSeparator","separator-8","openAsBookmarksPanel","openAsTabsPanel","separator-7","copyBookmarksUrls","copyBookmarksTitles","moveBookmarksTo","edit","delete"],"bookmarksPanel":["collapseAllFolders","switchViewMode","convertToTabsPanel","separator-9","unloadPanelType","openPanelConfig","hidePanel","removePanel"]},"sidebarCSS":"#root.root {--tabs-close-btn-margin: 3px;}\n#root.root {--general-margin: 0px;}\n#root {\n  --tabs-font: 9pt Segoe UI;\n  --tabs-count-font: .625rem Segoe UI;\n  --bookmarks-bookmark-font: .875rem Segoe UI;\n  --bookmarks-folder-font: 9pt Segoe UI;\n  --nav-btn-width: 42px;\n  --nav-btn-height: 42px;\n}\n\n/* Adjust styles according to sidebar width */\n@media screen and (max-width: 48px) {\n  #root {\n    --tabs-indent: unset;\n  }\n\n  .Tab .close {\n    visibility: hidden;\n  }\n\n  .BottomBar {\n    visibility: collapse;\n  }\n}\n\n#root {\n  --tabs-height: 36px;\n}\n\n#root:hover .Tab .close {\n  transition: visibility 0s 100ms;\n}\n\n.central-box {\n\tpadding-top: 5px;\n}\n\n.ScrollBox > .scroll-container {\n  width: calc(100% + 4px);\n  overflow-y: scroll;\n}\n\n.TabsPanel .new-tab-btns .new-tab-btn {\n  left: 2px;\n}\n\n.Tab[data-active=\"true\"] .body {\n  background: transparent;\n  box-shadow: none;\n}\n\n/* Background layer */\n.Tab .body:before {\n  content: '';\n  position: absolute;\n  left: 9px;\n  top: 3px;\n  width: calc(100% - 14px);\n  height: calc(100% - 6px);\n  border-radius: 4px;\n  z-index: -1;\n}\n\n.PinnedTabsBar .Tab .body:before {\n  width: calc(100% - 18px);\n}\n\n.Tab[data-active=\"true\"] .body:before,\n.Tab[data-active=\"true\"]:hover .body:before {\n  background-color: var(--frame-el-overlay-selected-bg);\n  box-shadow: 0px 3px 5px rgba(0, 0, 0, 0.5) !important;\n}\n\n.Tab[data-active=\"true\"][data-group=\"true\"] .ctx,\n.Tab[data-active=\"true\"][data-group=\"true\"][data-colorized=\"true\"] .color-layer {\n  box-shadow: 0px 3px 5px rgba(0, 0, 0, 0.5) !important;\n}\n\n/* Resize and reposition favicons */\n.Tab .fav {\n  margin-left: 16px !important;\n}\n\n.Tab .audio {\n  width: 16px !important;\n  height: 16px !important;\n  z-index: 21 !important;\n  left: calc(var(--tabs-inner-gap) + 24px) !important;\n}\n\n.Tab .close {\n  margin: 0px 2px;\n}\n\n.PinnedTabsBar .Tab .close {\n  margin: 0px 6px;\n}\n\n.Tab .t-box {\n  width: calc(100% - 50px);\n  mask: none !important;\n}\n\n.Tab:hover .t-box {\n  width: calc(100% - 70px);\n}\n\n.Tab .t-box .title {\n  text-overflow: ellipsis;\n}\n\n.Tab[data-audible=\"true\"] .t-box .title,\n.Tab[data-muted=\"true\"] .t-box .title,\n.Tab[data-paused=\"true\"] .t-box, .title {\n  transform: translateX(calc(var(--audio-btn-offset) / 2));\n}\n\n.Tab .ctx,\n.Tab[data-colorized=\"true\"] .color-layer {\n  height: calc(100% + 3px);\n  width: 3px;\n  left: 2px;\n  top: -6px;\n  opacity: 1 !important;\n  box-shadow: none;\n  border-radius: 0 0 3px 3px;\n}\n\n.Tab[data-group=\"true\"] + .Tab[data-group=\"false\"][data-color] .ctx,\n.Tab[data-group=\"true\"][data-colorized=\"true\"] + .Tab[data-parent=\"false\"][data-colorized=\"true\"] .color-layer {\n  top: 0;\n  height: calc(100% - 3px);\n  border-radius: 3px;\n}\n\n.Tab[data-parent=\"true\"][data-group=\"false\"][data-colorized=\"true\"] .color-layer {\n  top: 2px;\n  height: calc(100% - 5px);\n  border-radius: 3px;\n}\n\n.Tab[data-color],\n.Tab[data-colorized=\"true\"] {\n  padding-left: 0 !important;\n}\n\n.Tab[data-group=\"true\"][data-colorized=\"true\"] .body:before {\n  all: unset !important;\n}\n\n.Tab[data-group=\"true\"][data-colorized=\"true\"] .color-layer {\n  height: 24px;\n  width: calc(100% - 20px);\n  left: 12px;\n  top: 6px;\n  z-index: 0;\n  opacity: 1;\n  border-radius: 3px;\n}\n\n.Tab[data-group=\"true\"][data-colorized=\"true\"] .title {\n  color: black;\n}\n\n.Tab[data-group=\"true\"][data-colorized=\"true\"] .fav svg,\n.Tab[data-group=\"true\"][data-colorized=\"true\"] .close svg {\n  fill: black;\n}\n\n.Tab[data-group=\"true\"][data-colorized=\"true\"] .close {\n  --tabs-close-btn-margin: 6px;\n}\n\n.Tab[data-group=\"true\"][data-colorized=\"true\"] .t-box,\n.Tab[data-group=\"true\"][data-colorized=\"true\"] .close {\n  opacity: 1;\n}\n\n.Tab[data-group=\"true\"][data-colorized=\"true\"] .body .fav,\n.Tab[data-group=\"true\"][data-colorized=\"true\"] .fav .exp,\n.Tab[data-group=\"true\"][data-colorized=\"true\"] .fav .exp svg {\n  opacity: 1;\n}\n\n.Tab[data-group=\"true\"][data-colorized=\"true\"] .fav .fav-icon,\n.Tab[data-group=\"true\"][data-colorized=\"true\"] .fav .child-count {\n  display: none;\n}\n\n.Tab:hover .fav,\n.PinnedTab:hover .fav {\n  opacity: 1;\n}","groupCSS":"/* OLD CSS VARS\n#root.root {--bg: #0a0e14;}\n#root.root {--tabs-fg: #aaaaaa;}\n#root.root {--tabs-fg-hover: #ffffff;}\n#root.root {--tabs-bg-hover: #16202d;}\n#root.root {--tabs-bg-active: #16202d;}\n#root.root {--tabs-activated-bg: #16202d;}\n#root.root {--tabs-activated-fg: #ffffff;}\n#root.root {--tabs-selected-bg: #16202d;}\n#root.root {--tabs-selected-fg: #ffffff;}\n*/\n\n","ver":"5.0.0rc4"}